{
  "project_info": {
    "project_number": "125792106020",
    "project_id": "fitness-app-8000a",
    "storage_bucket": "fitness-app-8000a.appspot.com"
  },
  "client": [
    {
      "client_info": {
        "mobilesdk_app_id": "1:125792106020:android:b3fe8ef743e5c9a8d38ab1",
        "android_client_info": {
          "package_name": "com.isep.finalprojectfitnessapp"
        }
      },
      "oauth_client": [],
      "api_key": [
        {
          "current_key": "AIzaSyAjTE1wKfoJHF3eakXgRL8R1ho3Hj3KRl4"
        }
      ],
      "services": {
        "appinvite_service": {
          "other_platform_oauth_client": []
        }
      }
    }
  ],
  "configuration_version": "1"
}